{
  "parent": "minecraft:recipes/root",
  "rewards": {
    "recipes": [
      "mxtune:music_venue_tool"
    ]
  },
  "criteria": {
    "has_instrument": {
      "trigger": "minecraft:inventory_changed",
      "conditions": {
        "items": [
          {
            "item": "mxtune:multi_inst"
          }
        ]
      }
    },
    "has_rods_wooden": {
      "trigger": "minecraft:inventory_changed",
      "conditions": {
        "items": [
          {
            "tag": "forge:rods/wooden"
          }
        ]
      }
    },
    "has_the_recipe": {
      "trigger": "minecraft:recipe_unlocked",
      "conditions": {
        "recipe": "mxtune:music_venue_tool"
      }
    }
  },
  "requirements": [
    [
      "has_instrument",
      "has_rods_wooden",
      "has_the_recipe"
    ]
  ]
}